pyja/__main__.py
pyja-0.1.1.dist-info/licenses/LICENSE
pyja-0.1.1.dist-info/METADATA
pyja-0.1.1.dist-info/WHEEL
pyja-0.1.1.dist-info/entry_points.txt
pyja-0.1.1.dist-info/top_level.txt
pyja-0.1.1.dist-info/RECORD
