Metadata-Version: 2.4
Name: pyja
Version: 0.1.1
Summary: Run Python scripts with error messages translated into Japanese
Author: Your Name
License-File: LICENSE
Requires-Dist: deepl
Dynamic: license-file
